README.md
setup.py
py_attack_hyr/__init__.py
py_attack_hyr/new_attack_2.py
py_attack_hyr.egg-info/PKG-INFO
py_attack_hyr.egg-info/SOURCES.txt
py_attack_hyr.egg-info/dependency_links.txt
py_attack_hyr.egg-info/requires.txt
py_attack_hyr.egg-info/top_level.txt