Metadata-Version: 2.1
Name: py-attack-hyr
Version: 1.0.11
Summary: A test of py_attack
Author: hyr
Author-email: 
Keywords: python,menu,dumb_menu,windows,mac,linux
Classifier: Development Status :: 1 - Planning
Classifier: Intended Audience :: Developers
Classifier: Programming Language :: Python :: 3
Classifier: Operating System :: Unix
Classifier: Operating System :: MacOS :: MacOS X
Classifier: Operating System :: Microsoft :: Windows
